afids_cnn/__init__.py
afids_cnn/apply.py
afids_cnn/apply_workflow/config/snakebids.yml
afids_cnn/apply_workflow/run.py
afids_cnn/apply_workflow/workflow/Snakefile
afids_cnn/generator.py
afids_cnn/resources/tpl-MNI152NLin2009cAsym_res-01_T1w.fcsv
afids_cnn/resources/tpl-MNI152NLin2009cAsym_res-01_T1w.nii.gz
afids_cnn/train.py
afids_cnn/train_workflow/config/snakebids.yml
afids_cnn/train_workflow/run.py
afids_cnn/train_workflow/workflow/Snakefile
afids_cnn/train_workflow/workflow/scripts/assemble_models.py
afids_cnn/train_workflow/workflow/scripts/extract_afids.py
afids_cnn/utils.py
afids_cnn-0.2.1.dist-info/LICENSE
afids_cnn-0.2.1.dist-info/METADATA
afids_cnn-0.2.1.dist-info/entry_points.txt
afids_cnn-0.2.1.dist-info/WHEEL
afids_cnn-0.2.1.dist-info/RECORD
