Metadata-Version: 2.1
Name: afids-cnn
Version: 0.2.1
Summary: 
Author: Your Name
Author-email: you@example.com
Requires-Python: >=3.8,<3.12
Classifier: Programming Language :: Python :: 3
Classifier: Programming Language :: Python :: 3.8
Classifier: Programming Language :: Python :: 3.9
Classifier: Programming Language :: Python :: 3.10
Classifier: Programming Language :: Python :: 3.11
Requires-Dist: keras (>=2.12.0,<3.0.0)
Requires-Dist: numpy (>=1.22,<1.24)
Requires-Dist: pandas (>=1.3,<2)
Requires-Dist: scikit-image (>=0.19.3,<0.20.0)
Requires-Dist: snakebids (>=0.9.0,<0.10.0)
Requires-Dist: tensorflow (>=2.12.0,<3.0.0)
Requires-Dist: torch (>=1.13.1,<3.0.0)
